maxwelld/__init__.py
maxwelld/__main__.py
maxwelld/version
maxwelld/version.py
maxwelld/client/__init__.py
maxwelld/client/maxwell_client.py
maxwelld/client/types.py
maxwelld/core/__init__.py
maxwelld/core/compose_data_types.py
maxwelld/core/compose_instance.py
maxwelld/core/compose_instances.py
maxwelld/core/compose_interface.py
maxwelld/core/config.py
maxwelld/core/sequence_run_types.py
maxwelld/core/service.py
maxwelld/core/utils/__init__.py
maxwelld/core/utils/compose_files.py
maxwelld/core/utils/compose_instance_cfg.py
maxwelld/core/utils/env_files.py
maxwelld/core/utils/process_command_output.py
maxwelld/env_description/__init__.py
maxwelld/env_description/env_tools.py
maxwelld/env_description/env_types.py
maxwelld/errors/__init__.py
maxwelld/errors/migrations.py
maxwelld/errors/up.py
maxwelld/helpers/__init__.py
maxwelld/helpers/bytes_pickle.py
maxwelld/helpers/countdown_counter.py
maxwelld/helpers/exec_record.py
maxwelld/helpers/jobs_result.py
maxwelld/helpers/labels.py
maxwelld/helpers/state_keeper.py
maxwelld/output/__init__.py
maxwelld/output/console.py
maxwelld/output/styles.py
maxwelld/server/__init__.py
maxwelld/server/commands.py
maxwelld/server/maxwelld_server.py
maxwelld/server/handlers/__init__.py
maxwelld/server/handlers/dc_exec.py
maxwelld/server/handlers/dc_exec_logs.py
maxwelld/server/handlers/dc_logs.py
maxwelld/server/handlers/dc_up.py
maxwelld/server/handlers/env.py
maxwelld/server/handlers/healthcheck.py
maxwelld/server/handlers/status.py
maxwelld/server/handlers/up.py
maxwelld/vedro_plugin/__init__.py
maxwelld/vedro_plugin/env_setter.py
maxwelld/vedro_plugin/logger.py
maxwelld/vedro_plugin/plugin.py
maxwelld/vedro_plugin/scenario_ordering.py
maxwelld/vedro_plugin/scenario_tag_processing.py
maxwelld/vedro_plugin/state_waiting.py
maxwelld-2.1.5.dist-info/licenses/LICENSE
maxwelld-2.1.5.dist-info/METADATA
maxwelld-2.1.5.dist-info/WHEEL
maxwelld-2.1.5.dist-info/top_level.txt
maxwelld-2.1.5.dist-info/RECORD
